MRP/MRPAnalysis.py
MRP/MRPBaseSensor.py
MRP/MRPConfig.py
MRP/MRPDataVisualisationHelper.py
MRP/MRPDataVisualization.py
MRP/MRPHal.py
MRP/MRPHalHelper.py
MRP/MRPHalKlipper.py
MRP/MRPHalLocal.py
MRP/MRPHalRest.py
MRP/MRPHalSerialPortInformation.py
MRP/MRPHallbachArrayGenerator.py
MRP/MRPHelpers.py
MRP/MRPMagnetTypes.py
MRP/MRPMeasurementConfig.py
MRP/MRPOpenSCADGenerator.py
MRP/MRPPHalRestRequestResponseState.py
MRP/MRPPhysics.py
MRP/MRPPolarVisualization.py
MRP/MRPReading.py
MRP/MRPReadingEntry.py
MRP/MRPReadingSource.py
MRP/MRPReadingSourceFullsphere.py
MRP/MRPReadingSourceHelper.py
MRP/MRPReadingSourceStatic.py
MRP/MRPReadoutSource.py
MRP/MRPRotationalSensor.py
MRP/MRPSimulation.py
MRP/__init__.py
MRPcli/__init__.py
MRPcli/__main__.py
MRPcli/cli.py
MRPcli/cli_config.py
MRPcli/cli_datastorage.py
MRPcli/cli_helper.py
MRPcli/cli_measure.py
MRPcli/cli_proxy.py
MRPcli/cli_sensor.py
MRPcli/import_MRP.py
MRPcli/configs/MMC5603NJ_N=10000_AVG=5_RUN_1_MAGNET=1_config.json
MRPcli/configs/MMC5603NJ_N=10000_AVG_SAMPLES=1_RUN_1_config.json
MRPcli/configs/MMC5603NJ_N=10000_AVG_SAMPLES=5_RUN_1_config.json
MRPcli/configs/MMC5603NJ_N=1000_AVG=1_RUN_1_MAGNET=1_config.json
MRPcli/configs/MMC5603NJ_N=100_AVG=30_RUN_1_TEMPERATURE=50_config.json
MRPcli/configs/MMC5603NJ_N=2000_AVG=10_RUN_1_MAGNET=0_config.json
MRPcli/configs/MMC5603NJ_N=2000_AVG=10_RUN_1_MAGNET=1_config.json
MRPcli/configs/MMC5603NJ_N=2000_AVG=1_RUN_1_MAGNET=0_config.json
MRPcli/configs/MMC5603NJ_N=2000_AVG=1_RUN_1_MAGNET=1_config.json
MRPcli/configs/MMC5603NJ_N=2000_AVG=5_RUN_1_MAGNET=0_config.json
MRPcli/configs/MMC5603NJ_N=2000_AVG=5_RUN_1_MAGNET=1_config.json
MRPcli/configs/MMC5603NJ_N=2500_AVG=1_RUN_1_MAGNET=1_config.json
MRPcli/configs/MMC5603NJ_N=50_AVG=30_RUN_1_TEMPERATURE=20_config.json
MRPcli/configs/MMC5603NJ_N=50_AVG=30_RUN_1_TEMPERATURE=35_config.json
MRPcli/configs/MMC5603NJ_N=50_AVG=30_RUN_1_TEMPERATURE=50_config.json
MRPcli/configs/MMC5603_N=200_AVG=10_TEMPCURVE_config.json
MagneticReadoutProcessing-2.0.8.dist-info/LICENSE
MagneticReadoutProcessing-2.0.8.dist-info/METADATA
MagneticReadoutProcessing-2.0.8.dist-info/WHEEL
MagneticReadoutProcessing-2.0.8.dist-info/entry_points.txt
MagneticReadoutProcessing-2.0.8.dist-info/top_level.txt
MagneticReadoutProcessing-2.0.8.dist-info/RECORD
