Metadata-Version: 2.1
Name: MagneticReadoutProcessing
Version: 2.0.8
Summary: This library was created for the Low-Field MRI project and allows processing of data measured by magnetic field sensors. The focus is on visualization, followed by the provision of simple interfaces to work with this data. In general its possible to use this lib on all kinds of sensor data.
Home-page: https://github.com/LFB-MRI/MagnetCharacterization/
Author: Marcel Ochsendorf
Author-email: Marcel Ochsendorf <info@marcelochsendorf.com>
License: GNU GENERAL PUBLIC LICENSE
Project-URL: Homepage, https://github.com/LFB-MRI/MagneticReadoutProcessing
Project-URL: Bug Tracker, https://github.com/LFB-MRI/MagneticReadoutProcessing/issues
Project-URL: Documentation, https://magneticreadoutprocessing.readthedocs.io/en/latest/
Keywords: one,two
Classifier: Programming Language :: Python :: 3
Classifier: Operating System :: OS Independent
Requires-Python: >=3.7
License-File: LICENSE
Requires-Dist: pyserial>3.4.0
Requires-Dist: matplotlib>=3.5.3
Requires-Dist: numpy>=1.24.3
Requires-Dist: scipy>=1.10.0
Requires-Dist: lz4>=4.3.2
Requires-Dist: cobs>=1.2.0
Requires-Dist: ConfigParser>=5.3.0
Requires-Dist: tqdm>=4.65.0
Requires-Dist: magpylib>=4.2.0
Requires-Dist: magpy>=1.0.0
Requires-Dist: magpylib>=4.4.0
Requires-Dist: matplotlib>=3.7.3
Requires-Dist: pytest>=7.4.0
Requires-Dist: solid>=0.2.0
Requires-Dist: openpyscad>=0.5.0
Requires-Dist: vector>=1.1.0
Requires-Dist: vg>=2.0.0
Requires-Dist: click>=8.1.0
Requires-Dist: typer>=0.9.0
Requires-Dist: python-dotenv>=1.0.0
Requires-Dist: tinydb>=4.8.0
Requires-Dist: pyyaml>=6.0.1
Requires-Dist: pyvis>=0.3.2
Requires-Dist: waitress>=2.1.2
Requires-Dist: flask>=3.0.0
Requires-Dist: bleach>=6.0.0
Requires-Dist: flask-cors>=4.0.0
Requires-Dist: requests>=2.31.0
Requires-Dist: json-fix>=0.5.2
